odoo/addons/edi_sale_order_import_ubl_endpoint/README.rst
odoo/addons/edi_sale_order_import_ubl_endpoint/__init__.py
odoo/addons/edi_sale_order_import_ubl_endpoint/__manifest__.py
odoo/addons/edi_sale_order_import_ubl_endpoint/data/endpoint.xml
odoo/addons/edi_sale_order_import_ubl_endpoint/i18n/edi_sale_order_import_ubl_endpoint.pot
odoo/addons/edi_sale_order_import_ubl_endpoint/readme/CONTRIBUTORS.rst
odoo/addons/edi_sale_order_import_ubl_endpoint/readme/DESCRIPTION.rst
odoo/addons/edi_sale_order_import_ubl_endpoint/static/description/icon.png
odoo/addons/edi_sale_order_import_ubl_endpoint/static/description/index.html
odoo14_addon_edi_sale_order_import_ubl_endpoint-14.0.1.1.0.dist-info/METADATA
odoo14_addon_edi_sale_order_import_ubl_endpoint-14.0.1.1.0.dist-info/WHEEL
odoo14_addon_edi_sale_order_import_ubl_endpoint-14.0.1.1.0.dist-info/top_level.txt
odoo14_addon_edi_sale_order_import_ubl_endpoint-14.0.1.1.0.dist-info/RECORD
