Metadata-Version: 2.1
Name: odoo14-addon-edi-sale-order-import-ubl-endpoint
Version: 14.0.1.1.0
Summary: Provide a default endpoint to import SO in UBL format.
Home-page: https://github.com/OCA/edi
Author: Camptocamp,Odoo Community Association (OCA)
Author-email: support@odoo-community.org
License: AGPL-3
Platform: UNKNOWN
Classifier: Programming Language :: Python
Classifier: Framework :: Odoo
Classifier: Framework :: Odoo :: 14.0
Classifier: License :: OSI Approved :: GNU Affero General Public License v3
Classifier: Development Status :: 3 - Alpha
Requires-Python: >=3.6
Requires-Dist: odoo14-addon-edi-endpoint-oca
Requires-Dist: odoo14-addon-edi-sale-order-import
Requires-Dist: odoo14-addon-sale-order-import-ubl
Requires-Dist: odoo (<14.1dev,>=14.0a)
